invoicing/.env.example
invoicing/__init__.py
invoicing/__main__.py
invoicing/actions/__init__.py
invoicing/actions/action.py
invoicing/actions/action_collection.py
invoicing/api/__init__.py
invoicing/api/base_api.py
invoicing/api/client_api.py
invoicing/api/company_api.py
invoicing/api/index_api.py
invoicing/api/invoice_api.py
invoicing/api/job_api.py
invoicing/api/project_api.py
invoicing/api/staff_api.py
invoicing/api/status_api.py
invoicing/command_line.py
invoicing/constants/__init__.py
invoicing/constants/constants.py
invoicing/controller/__init__.py
invoicing/controller/main_controller.py
invoicing/crud/__init__.py
invoicing/crud/base_crud.py
invoicing/crud/client_crud.py
invoicing/crud/company_crud.py
invoicing/crud/invoice_crud.py
invoicing/crud/job_crud.py
invoicing/crud/project_crud.py
invoicing/crud/staff_crud.py
invoicing/crud/status_crud.py
invoicing/database/__init__.py
invoicing/database/sqlite3.py
invoicing/latex/__init__.py
invoicing/latex/latex_invoice.py
invoicing/latex/latex_quote.py
invoicing/latex/latex_templating.py
invoicing/logo.png
invoicing/model_validation/__init__.py
invoicing/model_validation/field.py
invoicing/model_validation/validation.py
invoicing/model_validation/validation_link.py
invoicing/model_validation/validations.py
invoicing/model_validation/validator.py
invoicing/models/__init__.py
invoicing/models/base_model.py
invoicing/models/client_model.py
invoicing/models/company_model.py
invoicing/models/invoice_model.py
invoicing/models/job_model.py
invoicing/models/project_model.py
invoicing/models/staff_model.py
invoicing/models/status_model.py
invoicing/query_builder/__init__.py
invoicing/query_builder/query_builder.py
invoicing/relationships/__init__.py
invoicing/relationships/base_relationship.py
invoicing/repository/__init__.py
invoicing/repository/base_repository.py
invoicing/repository/client_repository.py
invoicing/repository/company_repository.py
invoicing/repository/invoice_repository.py
invoicing-2.1.1.dist-info/entry_points.txt
invoicing-2.1.1.dist-info/LICENSE.txt
invoicing-2.1.1.dist-info/WHEEL
invoicing-2.1.1.dist-info/METADATA
invoicing-2.1.1.dist-info/RECORD
