Metadata-Version: 2.1
Name: invoicing
Version: 2.1.1
Summary: Generate invoice PDF from LaTeX template
License: MIT
Author: Sarcoma
Author-email: sean@orderandchaoscreative.com
Requires-Python: >=3.5,<4.0
Classifier: License :: OSI Approved :: MIT License
Classifier: Programming Language :: Python :: 3
Classifier: Programming Language :: Python :: 3.5
Classifier: Programming Language :: Python :: 3.6
Classifier: Programming Language :: Python :: 3.7
Classifier: Programming Language :: Python :: 3.8
Classifier: Programming Language :: Python :: 3.9
Requires-Dist: Flask (==1.0.2)
Requires-Dist: Jinja2 (==2.10.3)
Requires-Dist: Pygments (==2.2.0)
Requires-Dist: Werkzeug (==0.16.0)
Requires-Dist: ansi-colours (==0.2.6)
Requires-Dist: more-itertools (==4.3.0)
Requires-Dist: pytest (==3.10.0)
Requires-Dist: python-dateutil (==2.7.5)
Requires-Dist: python-dotenv (==0.9.1)
Requires-Dist: text-template (==0.1.4)
Requires-Dist: uWSGI (==2.0.17.1)
Requires-Dist: unicode (==2.6)
